admin_form_action/__init__.py
admin_form_action/py.typed
admin_form_action/templates/admin_form_action/form.html
django_admin_form_action-1.0.0.dist-info/LICENSE
django_admin_form_action-1.0.0.dist-info/METADATA
django_admin_form_action-1.0.0.dist-info/WHEEL
django_admin_form_action-1.0.0.dist-info/RECORD
