Metadata-Version: 2.1
Name: django-admin-form-action
Version: 1.0.0
Summary: Parametrized actions for Django admin site
Home-page: https://github.com/pauk-slon/django-admin-form-action
License: MIT
Keywords: django,admin,action
Author: Dmitry Kolyagin
Author-email: dmitry.kolyagin@gmail.com
Requires-Python: >=3.8,<4.0
Classifier: Framework :: Django :: 3
Classifier: Framework :: Django :: 4
Classifier: License :: OSI Approved :: MIT License
Classifier: Programming Language :: Python :: 3
Classifier: Programming Language :: Python :: 3.8
Classifier: Programming Language :: Python :: 3.9
Classifier: Programming Language :: Python :: 3.10
Classifier: Programming Language :: Python :: 3.11
Requires-Dist: django (>=3)
Project-URL: Repository, https://github.com/pauk-slon/django-admin-form-action
